CONTRIBUTING.rst
DEVELOP.rst
LICENSE
MANIFEST.in
NOTICE
README.rst
setup.cfg
setup.py
docs/requirements.txt
docs/_extra/robots.txt
src/crate/__init__.py
src/crate/client/__init__.py
src/crate/client/blob.py
src/crate/client/connection.py
src/crate/client/cursor.py
src/crate/client/exceptions.py
src/crate/client/http.py
src/crate/client/test_connection.py
src/crate/client/test_cursor.py
src/crate/client/test_http.py
src/crate/client/doctests/blob.txt
src/crate/client/doctests/client.txt
src/crate/client/doctests/connection.txt
src/crate/client/doctests/cursor.txt
src/crate/client/doctests/http.txt
src/crate/client/doctests/https.txt
src/crate/client/doctests/mocking.txt
src/crate/client/doctests/sqlalchemy.txt
src/crate/client/sqlalchemy/__init__.py
src/crate/client/sqlalchemy/compiler.py
src/crate/client/sqlalchemy/cratepg.py
src/crate/client/sqlalchemy/dialect.py
src/crate/client/sqlalchemy/sa_version.py
src/crate/client/sqlalchemy/types.py
src/crate/client/sqlalchemy/doctests/dialect.txt
src/crate/client/sqlalchemy/doctests/itests.txt
src/crate/client/sqlalchemy/doctests/reflection.txt
src/crate/client/sqlalchemy/predicates/__init__.py
src/crate/client/sqlalchemy/tests/__init__.py
src/crate/client/sqlalchemy/tests/array_test.py
src/crate/client/sqlalchemy/tests/bulk_test.py
src/crate/client/sqlalchemy/tests/compiler_test.py
src/crate/client/sqlalchemy/tests/connection_test.py
src/crate/client/sqlalchemy/tests/create_table_test.py
src/crate/client/sqlalchemy/tests/datetime_test.py
src/crate/client/sqlalchemy/tests/dialect_test.py
src/crate/client/sqlalchemy/tests/dict_test.py
src/crate/client/sqlalchemy/tests/function_test.py
src/crate/client/sqlalchemy/tests/insert_from_select_test.py
src/crate/client/sqlalchemy/tests/match_test.py
src/crate/client/sqlalchemy/tests/update_test.py
src/crate/testing/__init__.py
src/crate/testing/layer.py
src/crate/testing/test_layer.py
src/crate/testing/doctests/layer.txt
src/crate_smartnow.egg-info/PKG-INFO
src/crate_smartnow.egg-info/SOURCES.txt
src/crate_smartnow.egg-info/dependency_links.txt
src/crate_smartnow.egg-info/entry_points.txt
src/crate_smartnow.egg-info/namespace_packages.txt
src/crate_smartnow.egg-info/requires.txt
src/crate_smartnow.egg-info/top_level.txt