Metadata-Version: 2.1
Name: crate-smartnow
Version: 1.4.6
Summary: CrateDB Python Client
Home-page: https://github.com/Aymaru/crate-smartnow
Author: Crate.io
Author-email: office@crate.io
License: Apache License 2.0
Keywords: crate db api sqlalchemy
Platform: any
Classifier: Development Status :: 5 - Production/Stable
Classifier: Intended Audience :: Developers
Classifier: License :: OSI Approved :: Apache Software License
Classifier: Operating System :: OS Independent
Classifier: Programming Language :: Python
Classifier: Programming Language :: Python :: 3
Classifier: Programming Language :: Python :: 3.4
Classifier: Programming Language :: Python :: 3.5
Classifier: Programming Language :: Python :: 3.6
Classifier: Programming Language :: Python :: 3.7
Classifier: Programming Language :: Python :: 3.8
Classifier: Programming Language :: Python :: 3.9
Classifier: Programming Language :: Python :: Implementation :: CPython
Classifier: Programming Language :: Python :: Implementation :: PyPy
Classifier: Topic :: Database
Requires-Python: >=3.4
Provides-Extra: test
Provides-Extra: sqlalchemy
License-File: LICENSE
License-File: NOTICE
